nbxmpp_client/__init__.py
nbxmpp_client/application.py
nbxmpp_client/client.py
nbxmpp_client/main.py
nbxmpp_client/py.typed
nbxmpp_client/util.py
nbxmpp_client-2.0.1.dist-info/licenses/LICENSE
nbxmpp_client-2.0.1.dist-info/METADATA
nbxmpp_client-2.0.1.dist-info/WHEEL
nbxmpp_client-2.0.1.dist-info/entry_points.txt
nbxmpp_client-2.0.1.dist-info/top_level.txt
nbxmpp_client-2.0.1.dist-info/RECORD
