Metadata-Version: 2.4
Name: nbxmpp-client
Version: 2.0.1
Summary: XMPP Test Client
Author: Philipp Hörist
Author-email: philipp@hoerist.com
License: MIT
Project-URL: repository, https://dev.gajim.org/gajim/nbxmpp-client
Classifier: Programming Language :: Python :: 3.10
Requires-Python: >=3.10
License-File: LICENSE
Requires-Dist: nbxmpp<7.0.0,>=4.0.0
Provides-Extra: dev
Requires-Dist: isort; extra == "dev"
Requires-Dist: black; extra == "dev"
Requires-Dist: ruff; extra == "dev"
Dynamic: license-file
